odoo/addons/product_cost_rollup_to_bom/README.rst
odoo/addons/product_cost_rollup_to_bom/__init__.py
odoo/addons/product_cost_rollup_to_bom/__manifest__.py
odoo/addons/product_cost_rollup_to_bom/data/cost_rollup_scheduler.xml
odoo/addons/product_cost_rollup_to_bom/data/email_template.xml
odoo/addons/product_cost_rollup_to_bom/i18n/it.po
odoo/addons/product_cost_rollup_to_bom/i18n/product_cost_rollup_to_bom.pot
odoo/addons/product_cost_rollup_to_bom/models/__init__.py
odoo/addons/product_cost_rollup_to_bom/models/mrp_bom.py
odoo/addons/product_cost_rollup_to_bom/models/product.py
odoo/addons/product_cost_rollup_to_bom/models/res_config_settings.py
odoo/addons/product_cost_rollup_to_bom/readme/CONFIGURE.rst
odoo/addons/product_cost_rollup_to_bom/readme/CONTRIBUTORS.rst
odoo/addons/product_cost_rollup_to_bom/readme/DESCRIPTION.rst
odoo/addons/product_cost_rollup_to_bom/readme/USAGE.rst
odoo/addons/product_cost_rollup_to_bom/static/description/icon.png
odoo/addons/product_cost_rollup_to_bom/static/description/index.html
odoo/addons/product_cost_rollup_to_bom/views/mrp_bom.xml
odoo/addons/product_cost_rollup_to_bom/views/product_views.xml
odoo/addons/product_cost_rollup_to_bom/views/res_config_settings.xml
odoo13_addon_product_cost_rollup_to_bom-13.0.1.0.1.dev6.dist-info/METADATA
odoo13_addon_product_cost_rollup_to_bom-13.0.1.0.1.dev6.dist-info/WHEEL
odoo13_addon_product_cost_rollup_to_bom-13.0.1.0.1.dev6.dist-info/top_level.txt
odoo13_addon_product_cost_rollup_to_bom-13.0.1.0.1.dev6.dist-info/RECORD
